pysimtra/__init__.py
pysimtra/e_binding.csv
pysimtra/simtra_read.py
pysimtra/simtra_write.py
pysimtra/sputter_system.py
pysimtra/components/__init__.py
pysimtra/components/chamber.py
pysimtra/components/dummy_object.py
pysimtra/components/magnetron.py
pysimtra/simtra/__init__.py
pysimtra/simtra/simtra_output.py
pysimtra/surfaces/__init__.py
pysimtra/surfaces/circle.py
pysimtra/surfaces/cone.py
pysimtra/surfaces/cylinder.py
pysimtra/surfaces/plane.py
pysimtra/surfaces/rectangle.py
pysimtra/surfaces/sphere.py
pysimtra/surfaces/surface.py
pysimtra-1.0.3.dist-info/licenses/LICENSE
pysimtra-1.0.3.dist-info/METADATA
pysimtra-1.0.3.dist-info/WHEEL
pysimtra-1.0.3.dist-info/top_level.txt
pysimtra-1.0.3.dist-info/RECORD
