Metadata-Version: 2.4
Name: pysimtra
Version: 1.0.3
Summary: A package for simulating the transport of sputtered atoms for multiple magnetrons in parallel.
Author-email: Felix Thelen <felix.thelen@ruhr-uni-bochum.de>
License: 
Project-URL: Repository, https://github.com/felixthln/pysimtra
Project-URL: Documentation, https://pysimtra.readthedocs.io/en/latest/
Keywords: magnetron sputtering,monte carlo,sputter simulation,SIMTRA
Classifier: Intended Audience :: Science/Research
Classifier: Natural Language :: English
Classifier: Programming Language :: Python
Classifier: Operating System :: Microsoft :: Windows
Classifier: Programming Language :: Python :: 3
Classifier: Programming Language :: Python :: 3.9
Classifier: Programming Language :: Python :: 3.10
Classifier: Programming Language :: Python :: 3.11
Classifier: Programming Language :: Python :: 3.12
Requires-Python: >=3.9
License-File: LICENSE
Requires-Dist: numpy>=1.26.0
Requires-Dist: pandas>=2.1.1
Dynamic: license-file
